{
  "update_time": "2025-12-20T09:06:27.403899",
  "n_matches": 160,
  "date_range": "2025-08-15 to 2025-12-15",
  "teams": [
    "Arsenal",
    "Aston Villa",
    "Bournemouth",
    "Brentford",
    "Brighton",
    "Burnley",
    "Chelsea",
    "Crystal Palace",
    "Everton",
    "Fulham",
    "Leeds United",
    "Liverpool",
    "Manchester City",
    "Manchester Utd",
    "Newcastle Utd",
    "Nott'ham Forest",
    "Sunderland",
    "Tottenham",
    "West Ham",
    "Wolves"
  ],
  "rolling_window": 5,
  "dc_years_back": 3,
  "rho": 0.09435670175391456
}